crowdsourcehinter/__init__.py
crowdsourcehinter/crowdsourcehinter.py
crowdsourcehinter/public/3rdParty/mustache.js
crowdsourcehinter/static/README.txt
crowdsourcehinter/static/css/crowdsourcehinter.css
crowdsourcehinter/static/html/crowdsourcehinter.html
crowdsourcehinter/static/html/crowdsourcehinterstudio.html
crowdsourcehinter/static/js/src/crowdsourcehinter.js
crowdsourcehinter/static/js/src/crowdsourcehinter_studio.js
crowdsourcehinter_xblock-0.8.dist-info/LICENSE
crowdsourcehinter_xblock-0.8.dist-info/METADATA
crowdsourcehinter_xblock-0.8.dist-info/WHEEL
crowdsourcehinter_xblock-0.8.dist-info/entry_points.txt
crowdsourcehinter_xblock-0.8.dist-info/top_level.txt
crowdsourcehinter_xblock-0.8.dist-info/RECORD
