Metadata-Version: 2.1
Name: crowdsourcehinter-xblock
Version: 0.8
Summary: crowdsourcehinter XBlock
Home-page: https://github.com/openedx/crowdsourcehinter
Author: edX
Keywords: crowdsourcehinter xblock
Classifier: Development Status :: 3 - Alpha
Classifier: Intended Audience :: Developers
Classifier: Topic :: Software Development :: Build Tools
Classifier: License :: OSI Approved :: GNU Affero General Public License v3 or later (AGPLv3+)
Classifier: Programming Language :: Python :: 3
Classifier: Programming Language :: Python :: 3.11
Classifier: Programming Language :: Python :: 3.12
Classifier: Programming Language :: Python :: Implementation :: CPython
License-File: LICENSE
Requires-Dist: XBlock
Requires-Dist: six
Requires-Dist: web-fragments
